spyeeg/__init__.py
spyeeg/feat.py
spyeeg/generate.py
spyeeg/preproc.py
spyeeg/utils.py
spyeeg/version.py
spyeeg/viz.py
spyeeg/models/CCA.py
spyeeg/models/ERP.py
spyeeg/models/TRF.py
spyeeg/models/__init__.py
spyeeg/models/_methods.py
spyeeg-0.2.7.dist-info/METADATA
spyeeg-0.2.7.dist-info/WHEEL
spyeeg-0.2.7.dist-info/top_level.txt
spyeeg-0.2.7.dist-info/RECORD
