Metadata-Version: 2.4
Name: spyeeg
Version: 0.2.7
Summary: Package for modelling electrophysiological responses to stimuli
Author-email: Pierre Hieu Guilleminot <pierre.hieu.guilleminot@gmail.com>, Mikolaj Kegler <mikolajkegler@gmail.com>, Michael Thornton <m.thornton20@imperial.ac.uk>
License: BSD 3
Project-URL: Repository, https://github.com/phg17/sPyEEG
Requires-Python: >3.8
Requires-Dist: numpy
Requires-Dist: scipy
Requires-Dist: mne
Requires-Dist: scikit-learn
Requires-Dist: colorednoise
Requires-Dist: joblib
Requires-Dist: psutil
Requires-Dist: pandas
Requires-Dist: matplotlib
Requires-Dist: reservoirpy==0.3.15
Requires-Dist: netCDF4
Requires-Dist: h5netcdf
Requires-Dist: PyQt5
